{"chapterNum": "6", "hebrewText": ["﻿א: בִּשְׁנַת־מֹות֙ הַמֶּ֣לֶךְ עֻזִּיָּ֔הוּ", "וָאֶרְאֶ֧ה אֶת־אֲדֹנָ֛י יֹשֵׁ֥ב עַל־כִּסֵּ֖א רָ֣ם וְנִשָּׂ֑א", "וְשׁוּלָ֖יו מְלֵאִ֥ים אֶת־הַהֵיכָֽל׃", "ב: שְׂרָפִ֨ים עֹמְדִ֤ים׀ מִמַּ֙עַל֙ לֹ֔ו", "שֵׁ֧שׁ כְּנָפַ֛יִם שֵׁ֥שׁ כְּנָפַ֖יִם לְאֶחָ֑ד", "בִּשְׁתַּ֣יִם׀ יְכַסֶּ֣ה פָנָ֗יו", "וּבִשְׁתַּ֛יִם יְכַסֶּ֥ה רַגְלָ֖יו וּבִשְׁתַּ֥יִם יְעֹופֵֽף׃", "ג: וְקָרָ֨א זֶ֤ה אֶל־זֶה֙ וְאָמַ֔ר", "קָדֹ֧ושׁ׀ קָדֹ֛ושׁ קָדֹ֖ושׁ יְהוָ֣ה צְבָאֹ֑ות", "מְלֹ֥א כָל־הָאָ֖רֶץ כְּבֹודֹֽו׃", "ד: וַיָּנֻ֙עוּ֙ אַמֹּ֣ות הַסִּפִּ֔ים", "מִקֹּ֖ול הַקֹּורֵ֑א", "וְהַבַּ֖יִת יִמָּלֵ֥א עָשָֽׁן׃", "ה: וָאֹמַ֞ר אֹֽוי־לִ֣י כִֽי־נִדְמֵ֗יתִי", "כִּ֣י אִ֤ישׁ טְמֵֽא־שְׂפָתַ֙יִם֙ אָנֹ֔כִי", "וּבְתֹוךְ֙ עַם־טְמֵ֣א שְׂפָתַ֔יִם", "אָנֹכִ֖י יֹושֵׁ֑ב", "כִּ֗י", "אֶת־הַמֶּ֛לֶךְ יְהוָ֥ה צְבָאֹ֖ות רָא֥וּ עֵינָֽי׃", "ו: וַיָּ֣עָף אֵלַ֗י", "אֶחָד֙ מִן־הַשְּׂרָפִ֔ים", "וּבְיָדֹ֖ו רִצְפָּ֑ה", "בְּמֶ֨לְקַחַ֔יִם", "לָקַ֖ח מֵעַ֥ל הַמִּזְבֵּֽחַ׃", "ז: וַיַּגַּ֣ע עַל־פִּ֔י", "וַיֹּ֕אמֶר", "הִנֵּ֛ה נָגַ֥ע זֶ֖ה עַל־שְׂפָתֶ֑יךָ", "וְסָ֣ר עֲוֹנֶ֔ךָ", "וְחַטָּאתְךָ֖ תְּכֻפָּֽר׃", "ח: וָאֶשְׁמַ֞ע אֶת־קֹ֤ול אֲדֹנָי֙ אֹמֵ֔ר", "אֶת־מִ֥י אֶשְׁלַ֖ח וּמִ֣י יֵֽלֶךְ־לָ֑נוּ", "וָאֹמַ֖ר הִנְנִ֥י שְׁלָחֵֽנִי׃", "ט: וַיֹּ֕אמֶר", "לֵ֥ךְ וְאָמַרְתָּ֖ לָעָ֣ם הַזֶּ֑ה", "שִׁמְע֤וּ שָׁמֹ֙ועַ֙ וְאַל־תָּבִ֔ינוּ", "וּרְא֥וּ רָאֹ֖ו וְאַל־תֵּדָֽעוּ׃", "י: הַשְׁמֵן֙ לֵב־הָעָ֣ם הַזֶּ֔ה", "וְאָזְנָ֥יו הַכְבֵּ֖ד וְעֵינָ֣יו הָשַׁ֑ע", "פֶּן־יִרְאֶ֨ה בְעֵינָ֜יו", "וּבְאָזְנָ֣יו יִשְׁמָ֗ע", "וּלְבָבֹ֥ו יָבִ֛ין וָשָׁ֖ב וְרָ֥פָא לֹֽו׃", "יא: וָאֹמַ֕ר", "עַד־מָתַ֖י אֲדֹנָ֑י", "וַיֹּ֡אמֶר", "עַ֣ד אֲשֶׁר֩ אִם־שָׁא֨וּ עָרִ֜ים", "מֵאֵ֣ין יֹושֵׁ֗ב", "וּבָתִּים֙ מֵאֵ֣ין אָדָ֔ם", "וְהָאֲדָמָ֖ה תִּשָּׁאֶ֥ה שְׁמָמָֽה׃", "יב: וְרִחַ֥ק יְהוָ֖ה אֶת־הָאָדָ֑ם", "וְרַבָּ֥ה הָעֲזוּבָ֖ה בְּקֶ֥רֶב הָאָֽרֶץ׃", "יג: וְעֹ֥וד בָּהּ֙ עֲשִׂ֣רִיָּ֔ה", "וְשָׁ֖בָה וְהָיְתָ֣ה לְבָעֵ֑ר", "כָּאֵלָ֣ה וְכָאַלֹּ֗ון", "אֲשֶׁ֤ר בְּשַׁלֶּ֙כֶת֙ מַצֶּ֣בֶת בָּ֔ם", "זֶ֥רַע קֹ֖דֶשׁ מַצַּבְתָּֽהּ׃ פ", "\n"], "splitsAshk": ["0", "4461", "11789", "15789", "20181", "25821", "30290", "37421", "40760", "46789", "50421", "54229", "56570", "60821", "66090", "69789", "73229", "75480", "76949", "83210", "86250", "88480", "90909", "93141", "96920", "99701", "101509", "106410", "108509", "111949", "116949", "120749", "125269", "127141", "130901", "134221", "138079", "141229", "145149", "147770", "150781", "156109", "158239", "160661", "162909", "167570", "169880", "172749", "176629", "179880", "184501", "187661", "190381", "193469", "198000", "202109"], "splitsSeph": ["0", "4349", "10778", "14527", "18848", "23837", "28327", "34877", "37968", "44117", "47688", "51277", "53978", "57677", "62797", "66767", "69917", "72349", "73728", "79407", "82797", "85117", "87477", "89648", "93157", "95557", "97437", "101898", "104127", "107709", "112877", "115928", "119898", "121997", "125418", "129469", "132968", "136149", "140437", "142757", "145549", "151968", "154109", "156448", "158629", "163229", "165829", "168829", "172797", "175869", "180298", "183517", "186317", "189608", "193397", "197355"], "englishText": [["﻿1: In the year that king Uzziah died", "I saw the Lord sitting upon a throne high and lifted up,", "And His train filled the temple.", "2: Above Him stood the seraphim;", "each one had six wings:", "with twain he covered his face", "and with twain he covered his feet, and with twain he did fly.", "3: And one called unto another, and said:", "Holy, holy, holy, is the LORD of hosts;", "The whole earth is full of His glory.", "4: And the posts of the door were moved", "at the voice of them that called,", "and the house was filled with smoke.", "5: Then said I: Woe is me! for I am undone;", "Because I am a man of unclean lips,", "And in the midst of a people of unclean lips;", "I dwell", "For", "Mine eyes have seen the King,The LORD of hosts.", "6: Then flew unto me", "One of the seraphim,", "With a glowing stone in his hand,", "With tongs", "He had taken from off the altar;", "7: And he touched my mouth with it,", "And said:", "Lo, this hath touched thy lips;", "And thine iniquity is taken away,", "And thy sin expiated.", "8: And I heard the voice of the Lord, saying:", "Whom shall I send, and who will go for us", "Then I said: ‘Here am I; send me.’", "9: And He said:", "‘Go, and tell this people:", "Hear ye indeed, but understand not;", "And see ye indeed, but perceive not.", "10: Make the heart of this people fat,", "And make their ears heavy, and shut their eyes;", "Lest they, seeing with their eyes,", "And hearing with their ears,", "And understanding with their heart, return, and be healed.’", "11: Then said I:", "‘Lord, how long", "’", "And He answered:", "‘Until cities be waste", "without inhabitant,", "And houses without man,", "And the land become utterly waste,", "12: And the LORD have removed men far away,", "And the forsaken places be many in the midst of the land.", "13: And if there be yet a tenth in it,", "it shall again be eaten up;", "as a terebinth, and as an oak,", "whose stock remaineth, when they cast their leaves,", "so the holy seed shall be the stock thereof.’", "\n"]]}